calculadora_simples/__init__.py
calculadora_simples/operations.py
calculadora_simples_seu_nome-0.1.0.dist-info/METADATA
calculadora_simples_seu_nome-0.1.0.dist-info/WHEEL
calculadora_simples_seu_nome-0.1.0.dist-info/top_level.txt
calculadora_simples_seu_nome-0.1.0.dist-info/RECORD
